Workbook

Sheet Assumptions
A1: 3-Year TCO Model — Cloud vs On-Premises
A2: Infrastructure Placement Framework · 4th and Bailey · Module 2 · v1.0.0
A4: GENERAL ASSUMPTIONS
A5: Organisation name | B5: ENTER ORGANISATION NAME
A6: Workload / project name | B6: ENTER WORKLOAD NAME
A7: Assessment date | B7: May 2026
A8: Analysis period (years) | B8: 3
A9: Annual cost inflation rate | B9: 0.03
A11: CLOUD COSTS (ANNUAL — YEAR 1)
A12: Compute (VMs / containers / functions) | B12: 24000
A13: Storage (block, object, file) | B13: 8400
A14: Database (managed DB services) | B14: 12000
A15: Network — egress and data transfer | B15: 6000
A16: Security and compliance services | B16: 4800
A17: Backup and DR (cloud-native) | B17: 3600
A18: Support plan | B18: 2400
A19: SaaS licences (attributed to workload) | B19: 0
A20: Other cloud costs | B20: 0
A21: Total cloud Year 1 (annual) | B21: =SUM(B12:B20) -> 61200
A23: ON-PREMISES COSTS
A24: SERVER HARDWARE (one-time capex)
A25: Server hardware purchase / lease (Year 1) | B25: 60000
A26: Storage hardware | B26: 15000
A27: Network hardware (switches, firewall) | B27: 8000
A29: RECURRING ANNUAL COSTS
A30: Data centre / colocation (annual) | B30: 18000
A31: Power and cooling (annual) | B31: 6000
A32: Hardware maintenance contracts (annual) | B32: 8400
A33: Hypervisor / virtualisation licence (annual) | B33: 6000
A34: Backup solution licence (annual) | B34: 3600
A35: Monitoring and management tools (annual) | B35: 2400
A36: Security tools on-premises (annual) | B36: 4800
A37: IT staff time — incremental (annual) | B37: 24000
A38: Other on-premises costs | B38: 0

Sheet 3-Year TCO Model
A1: 3-Year Total Cost of Ownership — Cloud vs On-Premises
A3: Cost item | B3: Year 1 | C3: Year 2 | D3: Year 3 | E3: 3-Year Total
A4: OPTION A — PUBLIC CLOUD
A5: Compute | B5: =Assumptions!B12 -> 24000 | C5: =B5*(1+Assumptions!B9) -> 24720 | D5: =C5*(1+Assumptions!B9) -> 25461.6 | E5: =SUM(B5:D5) -> 74181.6
A6: Storage | B6: =Assumptions!B13 -> 8400 | C6: =B6*(1+Assumptions!B9) -> 8652 | D6: =C6*(1+Assumptions!B9) -> 8911.56 | E6: =SUM(B6:D6) -> 25963.56
A7: Database | B7: =Assumptions!B14 -> 12000 | C7: =B7*(1+Assumptions!B9) -> 12360 | D7: =C7*(1+Assumptions!B9) -> 12730.8 | E7: =SUM(B7:D7) -> 37090.8
A8: Network — egress | B8: =Assumptions!B15 -> 6000 | C8: =B8*(1+Assumptions!B9) -> 6180 | D8: =C8*(1+Assumptions!B9) -> 6365.4 | E8: =SUM(B8:D8) -> 18545.4
A9: Security services | B9: =Assumptions!B16 -> 4800 | C9: =B9*(1+Assumptions!B9) -> 4944 | D9: =C9*(1+Assumptions!B9) -> 5092.32 | E9: =SUM(B9:D9) -> 14836.32
A10: Backup and DR | B10: =Assumptions!B17 -> 3600 | C10: =B10*(1+Assumptions!B9) -> 3708 | D10: =C10*(1+Assumptions!B9) -> 3819.24 | E10: =SUM(B10:D10) -> 11127.24
A11: Support plan | B11: =Assumptions!B18 -> 2400 | C11: =B11*(1+Assumptions!B9) -> 2472 | D11: =C11*(1+Assumptions!B9) -> 2546.16 | E11: =SUM(B11:D11) -> 7418.16
A12: SaaS licences | B12: =Assumptions!B19 -> 0 | C12: =B12*(1+Assumptions!B9) -> 0 | D12: =C12*(1+Assumptions!B9) -> 0 | E12: =SUM(B12:D12) -> 0
A13: Other cloud costs | B13: =Assumptions!B20 -> 0 | C13: =B13*(1+Assumptions!B9) -> 0 | D13: =C13*(1+Assumptions!B9) -> 0 | E13: =SUM(B13:D13) -> 0
A14: TOTAL — Cloud (3-year) | B14: =SUM(B5:B13) -> 61200 | C14: =SUM(C5:C13) -> 63036 | D14: =SUM(D5:D13) -> 64927.08 | E14: =SUM(E5:E13) -> 189163.08
A16: OPTION B — ON-PREMISES / PRIVATE CLOUD
A17: Server hardware (capex — Year 1 only) | B17: 60000 | C17: 0 | D17: 0 | E17: =SUM(B17:D17) -> 60000
A18: Storage hardware (capex — Year 1 only) | B18: 15000 | C18: 0 | D18: 0 | E18: =SUM(B18:D18) -> 15000
A19: Network hardware (capex — Year 1 only) | B19: 8000 | C19: 0 | D19: 0 | E19: =SUM(B19:D19) -> 8000
A20: Data centre / colocation | B20: 18000 | C20: =B20*(1+Assumptions!B9) -> 18540 | D20: =C20*(1+Assumptions!B9) -> 19096.2 | E20: =SUM(B20:D20) -> 55636.2
A21: Power and cooling | B21: 6000 | C21: =B21*(1+Assumptions!B9) -> 6180 | D21: =C21*(1+Assumptions!B9) -> 6365.4 | E21: =SUM(B21:D21) -> 18545.4
A22: Hardware maintenance | B22: 8400 | C22: =B22*(1+Assumptions!B9) -> 8652 | D22: =C22*(1+Assumptions!B9) -> 8911.56 | E22: =SUM(B22:D22) -> 25963.56
A23: Hypervisor licence | B23: 6000 | C23: =B23*(1+Assumptions!B9) -> 6180 | D23: =C23*(1+Assumptions!B9) -> 6365.4 | E23: =SUM(B23:D23) -> 18545.4
A24: Backup solution | B24: 3600 | C24: =B24*(1+Assumptions!B9) -> 3708 | D24: =C24*(1+Assumptions!B9) -> 3819.24 | E24: =SUM(B24:D24) -> 11127.24
A25: Monitoring tools | B25: 2400 | C25: =B25*(1+Assumptions!B9) -> 2472 | D25: =C25*(1+Assumptions!B9) -> 2546.16 | E25: =SUM(B25:D25) -> 7418.16
A26: Security tools | B26: 4800 | C26: =B26*(1+Assumptions!B9) -> 4944 | D26: =C26*(1+Assumptions!B9) -> 5092.32 | E26: =SUM(B26:D26) -> 14836.32
A27: IT staff — incremental | B27: 24000 | C27: =B27*(1+Assumptions!B9) -> 24720 | D27: =C27*(1+Assumptions!B9) -> 25461.6 | E27: =SUM(B27:D27) -> 74181.6
A28: Other on-premises | B28: 0 | C28: =B28*(1+Assumptions!B9) -> 0 | D28: =C28*(1+Assumptions!B9) -> 0 | E28: =SUM(B28:D28) -> 0
A29: TOTAL — On-Premises (3-year) | B29: =SUM(B17:B28) -> 156200 | C29: =SUM(C17:C28) -> 75396 | D29: =SUM(D17:D28) -> 77657.88 | E29: =SUM(E17:E28) -> 309253.88
A31: COMPARISON SUMMARY
A32: Metric | B32: Year 1 | C32: Year 2 | D32: Year 3 | E32: 3-Year Total
A33: Cloud total cost | B33: =B14 -> 61200 | C33: =C14 -> 63036 | D33: =D14 -> 64927.08 | E33: =E14 -> 189163.08
A34: On-premises total cost | B34: =B29 -> 156200 | C34: =C29 -> 75396 | D34: =D29 -> 77657.88 | E34: =E29 -> 309253.88
A35: Difference (+ = cloud more expensive) | B35: =B33-B34 -> -95000 | C35: =C33-C34 -> -12360 | D35: =D33-D34 -> -12730.8 | E35: =E33-E34 -> -120090.8
A36: Cloud premium (%) | B36: =IF(B34=0,"-",(B33-B34)/B34) -> -0.60819462 | C36: =IF(C34=0,"-",(C33-C34)/C34) -> -0.16393443 | D36: =IF(D34=0,"-",(D33-D34)/D34) -> -0.16393443 | E36: =IF(E34=0,"-",(E33-E34)/E34) -> -0.38832431
A38: NOTE: A positive difference means cloud is more expensive over that period. This model is a starting point — customise inputs in the Assumptions sheet. Consult Module 1 for the full scored placement assessment.

Sheet Instructions
A1: How to use this model
A3: Step 1 — Assumptions tab
A4: Enter your organisation name, workload name, and assessment date in rows 5–7.
A5: Adjust the annual inflation rate (default 3%) in row 9.
A6: Update cloud cost line items in the CLOUD COSTS section with your actual cloud bills.
A7: Blue cells are inputs — enter your numbers there.
A9: Step 2 — 3-Year TCO Model tab
A10: The model auto-calculates Year 2 and Year 3 using the inflation rate from Assumptions.
A11: Update on-premises capex and opex rows with your actual quotes and estimates.
A12: Year 2 and Year 3 capex items (hardware) are set to zero — hardware is a one-time cost.
A13: The Comparison Summary at the bottom shows the 3-year cost differential.
A15: Step 3 — Interpret the results
... A28: github.com/4thandBailey/infrastructure-placement-framework · 4thandbailey.com · (888) 305-5977
